Metadata-Version: 1.2
Name: junopass-py
Version: 1.0.9
Summary: JunoPass support for Python.JunoPass provides a secure 2FA and Passwordless authentication.
Home-page: https://github.com/junopass/junopass-py
Author: Felix Cheruiyot
Author-email: felix@junopass.com
License: UNKNOWN
Platform: UNKNOWN
Classifier: Programming Language :: Python :: 3
Classifier: License :: OSI Approved :: MIT License
Classifier: Development Status :: 4 - Beta
Classifier: Intended Audience :: Developers
Classifier: Topic :: Security
Classifier: License :: OSI Approved :: MIT License
Requires-Python: >=3.6
